time_window/__init__.py
time_window/helpers.py
time_window/time_window.py
time_window-0.1.0.dist-info/LICENSE.txt
time_window-0.1.0.dist-info/METADATA
time_window-0.1.0.dist-info/WHEEL
time_window-0.1.0.dist-info/top_level.txt
time_window-0.1.0.dist-info/RECORD
