Metadata-Version: 2.1
Name: time-window
Version: 0.1.0
Summary: A Time Window library
Home-page: https://github.com/EncodeGroup/time-window
Author: Encode
Author-email: devs@encodegroup.com
License: UNKNOWN
Keywords: time window
Platform: UNKNOWN
Classifier: Development Status :: 3 - Alpha
Classifier: Intended Audience :: Developers
Classifier: Topic :: Software Development :: Libraries
Classifier: License :: OSI Approved :: Apache Software License
Classifier: Programming Language :: Python
Requires-Dist: babel (<3.0,>=2.1.1)
Requires-Dist: python-dateutil (<3.0,>=2.5.2)
